templater/__init__.py
templater/main.py
templater/templates.py
templater_cli-1.0.dist-info/METADATA
templater_cli-1.0.dist-info/WHEEL
templater_cli-1.0.dist-info/entry_points.txt
templater_cli-1.0.dist-info/top_level.txt
templater_cli-1.0.dist-info/RECORD
