Metadata-Version: 2.1
Name: templater-cli
Version: 1.0
Summary: Template Managing Tool
Home-page: https://github.com/sayampy/Template-Manager-Tool
Author: Sayam.py
Author-email: sujata.howrah.belgachia@gmail.com
License: MIT
Platform: UNKNOWN
Classifier: Programming Language :: Python :: 3
Classifier: License :: OSI Approved :: MIT License
Classifier: Operating System :: OS Independent
Requires-Dist: Click
